{
  "page": 1,
  "value": [
    {
      "path": "_news/2020-11-16-trump-allies-are-reportedly-considering-buying-out-newsmax-to-build-a-strong-competitor-to-fox-news.md",
      "title": "Trump allies are reportedly considering buying out Newsmax to build a strong competitor to Fox News",
      "excerpt": "Fox News viewers have been navigating over to Newsmax after the network declared Biden as the winner.",
      "sourceUrl": null,
      "webUrl": "https://www.businessinsider.com/trump-allies-considering-buying-out-newsmax-to-compete-against-fox-2020-11",
      "originalUrl": "https://www.businessinsider.com/trump-allies-considering-buying-out-newsmax-to-compete-against-fox-2020-11",
      "featuredContent": null,
      "highlight": null,
      "heat": 131,
      "tags": null,
      "images": [
        {
          "url": "https://i.insider.com/5fad9b5c1e8d50001981338a?width=1200&format=jpeg",
          "width": 1200,
          "height": 600,
          "title": null,
          "attribution": null,
          "isCached": true
        }
      ],
      "content": "\r\n",
      "type": "article",
      "ampWebUrl": "https://www.businessinsider.com/trump-allies-considering-buying-out-newsmax-to-compete-against-fox-2020-11?amp",
      "cdnAmpWebUrl": "https://www-businessinsider-com.cdn.ampproject.org/c/s/www.businessinsider.com/trump-allies-considering-buying-out-newsmax-to-compete-against-fox-2020-11?amp",
      "publishedDateTime": "2020-11-15T12:18:00-08:00",
      "updatedDateTime": null,
      "provider": {
        "name": "Business Insider",
        "domain": "businessinsider.com",
        "images": [
          {
            "url": "https://smartableai.github.io/election/assets/images/organizations/businessinsider.com-50x50.jpg",
            "width": 50,
            "height": 50,
            "title": null,
            "attribution": null,
            "isCached": false
          }
        ],
        "publishers": null,
        "authors": null
      },
      "locale": "en-us",
      "categories": [
        "news"
      ],
      "topics": [
        "Election",
        "Donald Trump"
      ]
    },
    {
      "path": "_news/2020-11-16-trump-allies-explored-buyout-of-newsmax-tv-as-fox-news-alternative.md",
      "title": "Trump Allies Explored Buyout of Newsmax TV as Fox News Alternative",
      "excerpt": "Hicks Equity Partners, a private-equity firm with ties to a co-chair of the Republican National Committee, has held talks in recent months about acquiring and investing in Newsmax, a fledgling pro-Trump cable channel.",
      "sourceUrl": null,
      "webUrl": "https://www.wsj.com/articles/trump-allies-explored-buyout-of-newsmax-tv-as-fox-news-alternative-11605464737",
      "originalUrl": "https://www.wsj.com/articles/trump-allies-explored-buyout-of-newsmax-tv-as-fox-news-alternative-11605464737",
      "featuredContent": null,
      "highlight": {
        "text": "Republican Voice",
        "textColor": "#FFFFFF",
        "backgroundColor": "#FF0000"
      },
      "heat": 135,
      "tags": null,
      "images": [
        {
          "url": "https://images.wsj.net/im-260269/social",
          "width": 1280,
          "height": 640,
          "title": null,
          "attribution": null,
          "isCached": true
        }
      ],
      "content": "\r\n",
      "type": "article",
      "ampWebUrl": "https://www.wsj.com/amp/articles/trump-allies-explored-buyout-of-newsmax-tv-as-fox-news-alternative-11605464737",
      "cdnAmpWebUrl": "https://www-wsj-com.cdn.ampproject.org/c/s/www.wsj.com/amp/articles/trump-allies-explored-buyout-of-newsmax-tv-as-fox-news-alternative-11605464737",
      "publishedDateTime": "2020-11-15T10:32:00-08:00",
      "updatedDateTime": null,
      "provider": {
        "name": "Wall Street Journal",
        "domain": "wsj.com",
        "images": [
          {
            "url": "https://smartableai.github.io/election/assets/images/organizations/wsj.com-50x50.jpg",
            "width": 50,
            "height": 50,
            "title": null,
            "attribution": null,
            "isCached": false
          }
        ],
        "publishers": null,
        "authors": null
      },
      "locale": "en-us",
      "categories": [
        "news"
      ],
      "topics": [
        "Election",
        "Donald Trump",
        "Republican Voice"
      ]
    },
    {
      "path": "_news/2020-11-15-trump-election-lawsuit-in-arizonas-maricopa-county-dismissed-outcome-wouldnt-have-affected-races.md",
      "title": "Trump election lawsuit in Arizona's Maricopa County dismissed, outcome wouldn't have affected races",
      "excerpt": "By Friday morning, the Trump team had filed a motion acknowledging the outcome of the lawsuit would have no impact on Arizona’s presidential results",
      "sourceUrl": null,
      "webUrl": "https://www.usatoday.com/story/news/politics/elections/2020/11/14/trump-lawsuit-arizonas-maricopa-county-dismissed-judge/6296977002/",
      "originalUrl": "https://www.usatoday.com/story/news/politics/elections/2020/11/14/trump-lawsuit-arizonas-maricopa-county-dismissed-judge/6296977002/",
      "featuredContent": null,
      "highlight": null,
      "heat": 166,
      "tags": null,
      "images": [
        {
          "url": "https://www.gannett-cdn.com/presto/2020/11/12/PPHX/353c4712-7112-4185-8090-fa36aadc45e8-DW1_4295.JPG?auto=webp&crop=3521,1981,x0,y0&format=pjpg&width=1200",
          "width": 1200,
          "height": 675,
          "title": null,
          "attribution": null,
          "isCached": true
        }
      ],
      "content": "\r\n",
      "type": "article",
      "ampWebUrl": "https://amp.usatoday.com/amp/6296977002",
      "cdnAmpWebUrl": "https://amp-usatoday-com.cdn.ampproject.org/c/s/amp.usatoday.com/amp/6296977002",
      "publishedDateTime": "2020-11-14T12:03:00-08:00",
      "updatedDateTime": null,
      "provider": {
        "name": "USA Today",
        "domain": "usatoday.com",
        "images": [
          {
            "url": "https://smartableai.github.io/election/assets/images/organizations/usatoday.com-50x50.jpg",
            "width": 50,
            "height": 50,
            "title": null,
            "attribution": null,
            "isCached": false
          }
        ],
        "publishers": null,
        "authors": null
      },
      "locale": "en-us",
      "categories": [
        "news"
      ],
      "topics": [
        "Election",
        "Donald Trump"
      ]
    },
    {
      "path": "_news/2020-11-15-trump-team-mocked-for-apparently-exaggerating-crowd-size-againthis-time-for-million-maga-march.md",
      "title": "Trump Team Mocked For Apparently Exaggerating Crowd Size (Again)—This Time For ‘Million Maga March’",
      "excerpt": "The White House seems to have again been caught in a fib when it comes to overstating crowd size, after Press Secretary Kayleigh McEnany claimed Saturday that “More than one MILLION” marchers descended on Washington for the “Million MAGA March” in support of President Donald Trump—a claim that many on social media pointed out seemed to be greatly overstated based on actual pictures of the event.",
      "sourceUrl": null,
      "webUrl": "https://www.forbes.com/sites/nicholasreimann/2020/11/14/trump-team-mocked-for-apparently-exaggerating-crowd-size-again-this-time-for-million-maga-march/",
      "originalUrl": "https://www.forbes.com/sites/nicholasreimann/2020/11/14/trump-team-mocked-for-apparently-exaggerating-crowd-size-again-this-time-for-million-maga-march/",
      "featuredContent": null,
      "highlight": null,
      "heat": 111,
      "tags": null,
      "images": [
        {
          "url": "https://thumbor.forbes.com/thumbor/fit-in/1200x0/filters%3Aformat%28jpg%29/https%3A%2F%2Fspecials-images.forbesimg.com%2Fimageserve%2F5fb025d66f575407a5a3b7d1%2F0x0.jpg%3FcropX1%3D0%26cropX2%3D5472%26cropY1%3D277%26cropY2%3D3355",
          "width": 1200,
          "height": 675,
          "title": null,
          "attribution": null,
          "isCached": true
        }
      ],
      "content": "\r\n",
      "type": "article",
      "ampWebUrl": "https://www.forbes.com/sites/nicholasreimann/2020/11/14/trump-team-mocked-for-apparently-exaggerating-crowd-size-again-this-time-for-million-maga-march/amp/",
      "cdnAmpWebUrl": "https://www-forbes-com.cdn.ampproject.org/c/s/www.forbes.com/sites/nicholasreimann/2020/11/14/trump-team-mocked-for-apparently-exaggerating-crowd-size-again-this-time-for-million-maga-march/amp/",
      "publishedDateTime": "2020-11-14T10:54:00-08:00",
      "updatedDateTime": null,
      "provider": {
        "name": "Forbes",
        "domain": "forbes.com",
        "images": [
          {
            "url": "https://smartableai.github.io/election/assets/images/organizations/forbes.com-50x50.jpg",
            "width": 50,
            "height": 50,
            "title": null,
            "attribution": null,
            "isCached": false
          }
        ],
        "publishers": null,
        "authors": null
      },
      "locale": "en-us",
      "categories": [
        "news"
      ],
      "topics": [
        "Election",
        "Donald Trump"
      ]
    },
    {
      "path": "_news/2020-11-15-philadelphia-suburbs-return-with-a-vengeance-to-oust-trump.md",
      "title": "Philadelphia suburbs return with a vengeance to oust Trump",
      "excerpt": "Voters in Philadelphia’s suburbs hurled perhaps their biggest rebuke yet this month to President Donald Trump and the Republican Party overall",
      "sourceUrl": null,
      "webUrl": "https://www.washingtonpost.com/politics/philadelphia-suburbs-return-with-a-vengeance-to-oust-trump/2020/11/14/63c9f154-2697-11eb-9c4a-0dc6242c4814_story.html",
      "originalUrl": "https://www.washingtonpost.com/politics/philadelphia-suburbs-return-with-a-vengeance-to-oust-trump/2020/11/14/63c9f154-2697-11eb-9c4a-0dc6242c4814_story.html",
      "featuredContent": null,
      "highlight": null,
      "heat": 145,
      "tags": null,
      "images": [
        {
          "url": "https://www.washingtonpost.com/resizer/2CjPNwqvXHPS_2RpuRTKY-p3eVo=/1484x0/www.washingtonpost.com/pb/resources/img/twp-social-share.png",
          "width": 1484,
          "height": 779,
          "title": null,
          "attribution": null,
          "isCached": true
        }
      ],
      "content": "\r\n",
      "type": "article",
      "ampWebUrl": "https://www.washingtonpost.com/politics/philadelphia-suburbs-return-with-a-vengeance-to-oust-trump/2020/11/14/63c9f154-2697-11eb-9c4a-0dc6242c4814_story.html?outputType=amp",
      "cdnAmpWebUrl": "https://www-washingtonpost-com.cdn.ampproject.org/c/s/www.washingtonpost.com/politics/philadelphia-suburbs-return-with-a-vengeance-to-oust-trump/2020/11/14/63c9f154-2697-11eb-9c4a-0dc6242c4814_story.html?outputType=amp",
      "publishedDateTime": "2020-11-14T08:35:00-08:00",
      "updatedDateTime": null,
      "provider": {
        "name": "Washington Post",
        "domain": "washingtonpost.com",
        "images": [
          {
            "url": "https://smartableai.github.io/election/assets/images/organizations/washingtonpost.com-50x50.jpg",
            "width": 50,
            "height": 50,
            "title": null,
            "attribution": null,
            "isCached": false
          }
        ],
        "publishers": null,
        "authors": null
      },
      "locale": "en-us",
      "categories": [
        "news"
      ],
      "topics": [
        "Election",
        "Donald Trump"
      ]
    },
    {
      "path": "_news/2020-11-14-rudy-giuliani-is-reportedly-taking-charge-in-trumps-election-legal-battles-and-twitter-is-having-a-field-day-with-it.md",
      "title": "Rudy Giuliani is reportedly taking charge in Trump's election legal battles — and Twitter is having a field day with it",
      "excerpt": "\"Rudy will soon be appealing all of these adverse rulings to the Supreme Courtyard by Marriott,\" one person tweeted.",
      "sourceUrl": null,
      "webUrl": "https://www.businessinsider.com/twitter-reacts-to-rudy-giuliani-taking-over-trumps-election-lawsuits-2020-11",
      "originalUrl": "https://www.businessinsider.com/twitter-reacts-to-rudy-giuliani-taking-over-trumps-election-lawsuits-2020-11",
      "featuredContent": null,
      "highlight": null,
      "heat": 156,
      "tags": null,
      "images": [
        {
          "url": "https://i.insider.com/5faf7e29402d49001924efb8?width=1200&format=jpeg",
          "width": 1200,
          "height": 600,
          "title": null,
          "attribution": null,
          "isCached": true
        }
      ],
      "content": "\r\n",
      "type": "article",
      "ampWebUrl": "https://www.businessinsider.com/twitter-reacts-to-rudy-giuliani-taking-over-trumps-election-lawsuits-2020-11?amp",
      "cdnAmpWebUrl": "https://www-businessinsider-com.cdn.ampproject.org/c/s/www.businessinsider.com/twitter-reacts-to-rudy-giuliani-taking-over-trumps-election-lawsuits-2020-11?amp",
      "publishedDateTime": "2020-11-13T23:21:00-08:00",
      "updatedDateTime": null,
      "provider": {
        "name": "Business Insider",
        "domain": "businessinsider.com",
        "images": [
          {
            "url": "https://smartableai.github.io/election/assets/images/organizations/businessinsider.com-50x50.jpg",
            "width": 50,
            "height": 50,
            "title": null,
            "attribution": null,
            "isCached": false
          }
        ],
        "publishers": null,
        "authors": null
      },
      "locale": "en-us",
      "categories": [
        "news"
      ],
      "topics": [
        "Election",
        "Donald Trump"
      ]
    },
    {
      "path": "_news/2020-11-14-trump-supporters-plan-rallies-in-washington-dc-experts-warn-extremists-may-attend.md",
      "title": "Trump supporters plan rallies in Washington DC, experts warn extremists may attend",
      "excerpt": "It's unclear how many people will go to rallies in support of President Trump in Washington, D.C., but experts warn right-wing extremists may attend.",
      "sourceUrl": null,
      "webUrl": "https://www.usatoday.com/story/news/nation/2020/11/13/trump-supporters-plan-washington-dc-rallies-experts-warn-extremists/6265591002/",
      "originalUrl": "https://www.usatoday.com/story/news/nation/2020/11/13/trump-supporters-plan-washington-dc-rallies-experts-warn-extremists/6265591002/",
      "featuredContent": null,
      "highlight": null,
      "heat": 139,
      "tags": null,
      "images": [
        {
          "url": "https://www.gannett-cdn.com/presto/2020/11/07/USAT/c9445b3e-4891-4b6d-8858-278174f9fa31-XXX_ILSPR_110720_PHOTO_Rally_03.jpg?auto=webp&crop=4533,2550,x0,y389&format=pjpg&width=1200",
          "width": 1200,
          "height": 675,
          "title": null,
          "attribution": null,
          "isCached": true
        }
      ],
      "content": "\r\n",
      "type": "article",
      "ampWebUrl": "https://amp.usatoday.com/amp/6265591002",
      "cdnAmpWebUrl": "https://amp-usatoday-com.cdn.ampproject.org/c/s/amp.usatoday.com/amp/6265591002",
      "publishedDateTime": "2020-11-13T20:35:00-08:00",
      "updatedDateTime": null,
      "provider": {
        "name": "USA Today",
        "domain": "usatoday.com",
        "images": [
          {
            "url": "https://smartableai.github.io/election/assets/images/organizations/usatoday.com-50x50.jpg",
            "width": 50,
            "height": 50,
            "title": null,
            "attribution": null,
            "isCached": false
          }
        ],
        "publishers": null,
        "authors": null
      },
      "locale": "en-us",
      "categories": [
        "news"
      ],
      "topics": [
        "Election",
        "Donald Trump"
      ]
    },
    {
      "path": "_news/2020-11-14-not-credible-michigan-court-ruling-another-legal-setback-for-president-trump.md",
      "title": "'Not credible': Michigan court ruling another legal setback for President Trump",
      "excerpt": "A Michigan judge has denied a petition to block the certification of the 2020 election results in the heavily Democratic county that is home to Detroit, another legal setback for the Trump campaign, which has similar cases in several states.",
      "sourceUrl": null,
      "webUrl": "https://abcnews.go.com/Politics/credible-michigan-court-ruling-legal-setback-president-trump/story?id=74199110",
      "originalUrl": "https://abcnews.go.com/Politics/credible-michigan-court-ruling-legal-setback-president-trump/story?id=74199110",
      "featuredContent": null,
      "highlight": null,
      "heat": 121,
      "tags": null,
      "images": [
        {
          "url": "https://s.abcnews.com/images/Politics/counting-ballots-michigan-ap-jt-201113_1605303384179_hpMain_16x9_992.jpg",
          "width": 992,
          "height": 558,
          "title": null,
          "attribution": null,
          "isCached": true
        }
      ],
      "content": "\r\n",
      "type": "article",
      "ampWebUrl": "https://abcnews.go.com/amp/Politics/credible-michigan-court-ruling-legal-setback-president-trump/story?id=74199110",
      "cdnAmpWebUrl": "https://abcnews-go-com.cdn.ampproject.org/c/s/abcnews.go.com/amp/Politics/credible-michigan-court-ruling-legal-setback-president-trump/story?id=74199110",
      "publishedDateTime": "2020-11-13T18:57:00-08:00",
      "updatedDateTime": null,
      "provider": {
        "name": "ABC",
        "domain": "abcnews.go.com",
        "images": [
          {
            "url": "https://smartableai.github.io/election/assets/images/organizations/abcnews.go.com-50x50.jpg",
            "width": 50,
            "height": 50,
            "title": null,
            "attribution": null,
            "isCached": false
          }
        ],
        "publishers": null,
        "authors": null
      },
      "locale": "en-us",
      "categories": [
        "news"
      ],
      "topics": [
        "Election",
        "Donald Trump"
      ]
    },
    {
      "path": "_news/2020-11-14-trump-to-break-silence-with-vaccine-update-after-criticism-hes-ignored-pandemic.md",
      "title": "Trump to break silence with vaccine update after criticism he's ignored pandemic",
      "excerpt": "President Donald Trump was scheduled to speak about the federal government's coronavirus vaccine program after criticism he has been ignoring the pandemic.",
      "sourceUrl": null,
      "webUrl": "https://abcnews.go.com/Politics/trump-vaccine-update-criticism-pandemic-defeat/story?id=74190881",
      "originalUrl": "https://abcnews.go.com/Politics/trump-vaccine-update-criticism-pandemic-defeat/story?id=74190881",
      "featuredContent": null,
      "highlight": null,
      "heat": 140,
      "tags": null,
      "images": [
        {
          "url": "https://s.abcnews.com/images/US/trump-arlington-cemetery-03-ap-jc-201111_1605113975110_hpMain_16x9_992.jpg",
          "width": 992,
          "height": 558,
          "title": null,
          "attribution": null,
          "isCached": true
        }
      ],
      "content": "\r\n",
      "type": "article",
      "ampWebUrl": "https://abcnews.go.com/amp/Politics/trump-vaccine-update-criticism-pandemic-defeat/story?id=74190881",
      "cdnAmpWebUrl": "https://abcnews-go-com.cdn.ampproject.org/c/s/abcnews.go.com/amp/Politics/trump-vaccine-update-criticism-pandemic-defeat/story?id=74190881",
      "publishedDateTime": "2020-11-13T14:31:00-08:00",
      "updatedDateTime": null,
      "provider": {
        "name": "ABC",
        "domain": "abcnews.go.com",
        "images": [
          {
            "url": "https://smartableai.github.io/election/assets/images/organizations/abcnews.go.com-50x50.jpg",
            "width": 50,
            "height": 50,
            "title": null,
            "attribution": null,
            "isCached": false
          }
        ],
        "publishers": null,
        "authors": null
      },
      "locale": "en-us",
      "categories": [
        "news"
      ],
      "topics": [
        "Election",
        "Donald Trump"
      ]
    },
    {
      "path": "_news/2020-11-14-rebuking-trump-dhs-cybersecurity-agency-says-no-evidence-of-deleted-changed-votes.md",
      "title": "Rebuking Trump, DHS cybersecurity agency says no evidence of deleted, changed votes",
      "excerpt": "Rebuking Trump, the Department of Homeland Security's cybersecurity agency says there is no evidence of deleted or changed votes.",
      "sourceUrl": null,
      "webUrl": "https://abcnews.go.com/Politics/rebuking-trump-dhs-cybersecurity-agency-evidence-deleted-changed/story?id=74188202",
      "originalUrl": "https://abcnews.go.com/Politics/rebuking-trump-dhs-cybersecurity-agency-evidence-deleted-changed/story?id=74188202",
      "featuredContent": null,
      "highlight": null,
      "heat": 119,
      "tags": null,
      "images": [
        {
          "url": "https://s.abcnews.com/images/US/DHS-gty-er-201020_1603231692954_hpMain_16x9_992.jpg",
          "width": 992,
          "height": 558,
          "title": null,
          "attribution": null,
          "isCached": true
        }
      ],
      "content": "\r\n",
      "type": "article",
      "ampWebUrl": "https://abcnews.go.com/amp/Politics/rebuking-trump-dhs-cybersecurity-agency-evidence-deleted-changed/story?id=74188202",
      "cdnAmpWebUrl": "https://abcnews-go-com.cdn.ampproject.org/c/s/abcnews.go.com/amp/Politics/rebuking-trump-dhs-cybersecurity-agency-evidence-deleted-changed/story?id=74188202",
      "publishedDateTime": "2020-11-13T09:21:00-08:00",
      "updatedDateTime": null,
      "provider": {
        "name": "ABC",
        "domain": "abcnews.go.com",
        "images": [
          {
            "url": "https://smartableai.github.io/election/assets/images/organizations/abcnews.go.com-50x50.jpg",
            "width": 50,
            "height": 50,
            "title": null,
            "attribution": null,
            "isCached": false
          }
        ],
        "publishers": null,
        "authors": null
      },
      "locale": "en-us",
      "categories": [
        "news"
      ],
      "topics": [
        "Election",
        "Donald Trump"
      ]
    },
    {
      "path": "_news/2020-11-13-the-technology-202-trump-will-face-new-rules-on-facebook-and-twitter-after-he-leaves-office.md",
      "title": "The Technology 202: Trump will face new rules on Facebook and Twitter after he leaves office",
      "excerpt": "The president will no longer have special protections afforded to elected officials. But a 2024 run could change that.",
      "sourceUrl": null,
      "webUrl": "https://www.washingtonpost.com/politics/2020/11/13/technology-202-trump-will-have-new-rules-facebook-twitter-after-he-leaves-office/",
      "originalUrl": "https://www.washingtonpost.com/politics/2020/11/13/technology-202-trump-will-have-new-rules-facebook-twitter-after-he-leaves-office/",
      "featuredContent": null,
      "highlight": null,
      "heat": 114,
      "tags": null,
      "images": [
        {
          "url": "https://www.washingtonpost.com/wp-apps/imrs.php?src=https://arc-anglerfish-washpost-prod-washpost.s3.amazonaws.com/public/YHQZNSBFNUI6XHCKBXDCILCICQ.jpg&w=1440",
          "width": 1440,
          "height": 960,
          "title": null,
          "attribution": null,
          "isCached": true
        }
      ],
      "content": "\r\n",
      "type": "article",
      "ampWebUrl": "https://www.washingtonpost.com/politics/2020/11/13/technology-202-trump-will-have-new-rules-facebook-twitter-after-he-leaves-office/?outputType=amp",
      "cdnAmpWebUrl": "https://www-washingtonpost-com.cdn.ampproject.org/c/s/www.washingtonpost.com/politics/2020/11/13/technology-202-trump-will-have-new-rules-facebook-twitter-after-he-leaves-office/?outputType=amp",
      "publishedDateTime": "2020-11-13T06:04:00-08:00",
      "updatedDateTime": null,
      "provider": {
        "name": "Washington Post",
        "domain": "washingtonpost.com",
        "images": [
          {
            "url": "https://smartableai.github.io/election/assets/images/organizations/washingtonpost.com-50x50.jpg",
            "width": 50,
            "height": 50,
            "title": null,
            "attribution": null,
            "isCached": false
          }
        ],
        "publishers": null,
        "authors": null
      },
      "locale": "en-us",
      "categories": [
        "news"
      ],
      "topics": [
        "Election",
        "Donald Trump"
      ]
    },
    {
      "path": "_news/2020-11-13-trump-bans-us-investments-in-firms-linked-to-chinese-military.md",
      "title": "Trump bans U.S. investments in firms linked to Chinese military",
      "excerpt": "The Trump administration on Thursday unveiled an executive order prohibiting U.S. investments in Chinese firms that Washington says are owned or controlled by the Chinese military, ramping up pressure on Beijing after the U.",
      "sourceUrl": null,
      "webUrl": "https://www.reuters.com/article/us-usa-china-securities-exclusive-idUKKBN27S2X3",
      "originalUrl": "https://www.reuters.com/article/us-usa-china-securities-exclusive-idUKKBN27S2X3",
      "featuredContent": null,
      "highlight": null,
      "heat": 225,
      "tags": null,
      "images": [
        {
          "url": "https://s4.reutersmedia.net/resources/r/?m=02&d=20201113&t=2&i=1541108180&w=&fh=545px&fw=&ll=&pl=&sq=&r=LYNXMPEGAC0WZ",
          "width": 817,
          "height": 545,
          "title": null,
          "attribution": null,
          "isCached": true
        }
      ],
      "content": "\r\n",
      "type": "article",
      "ampWebUrl": "https://mobile.reuters.com/article/amp/idUKKBN27S2X3",
      "cdnAmpWebUrl": "https://mobile-reuters-com.cdn.ampproject.org/c/s/mobile.reuters.com/article/amp/idUKKBN27S2X3",
      "publishedDateTime": "2020-11-13T04:58:00-08:00",
      "updatedDateTime": null,
      "provider": {
        "name": "Reuters",
        "domain": "reuters.com",
        "images": [
          {
            "url": "https://smartableai.github.io/election/assets/images/organizations/reuters.com-50x50.jpg",
            "width": 50,
            "height": 50,
            "title": null,
            "attribution": null,
            "isCached": false
          }
        ],
        "publishers": null,
        "authors": null
      },
      "locale": "en-us",
      "categories": [
        "news"
      ],
      "topics": [
        "Election",
        "Donald Trump"
      ]
    },
    {
      "path": "_news/2020-11-13-why-did-the-polls-undercount-trump-voters.md",
      "title": "Why did the polls undercount Trump voters?",
      "excerpt": "However, some state polls did underestimate Trump support. For example, polls in Iowa showed a 1 percent Trump advantage, but he won by about 8 percent. Polls in Pennsylvania showed a 5 percent Biden advantage,",
      "sourceUrl": null,
      "webUrl": "https://www.washingtonpost.com/politics/2020/11/13/why-did-polls-undercount-trump-voters/",
      "originalUrl": "https://www.washingtonpost.com/politics/2020/11/13/why-did-polls-undercount-trump-voters/",
      "featuredContent": null,
      "highlight": null,
      "heat": 205,
      "tags": null,
      "images": [
        {
          "url": "https://www.washingtonpost.com/wp-apps/imrs.php?src=https://arc-anglerfish-washpost-prod-washpost.s3.amazonaws.com/public/YUQALGBEJUI6XHCKBXDCILCICQ.jpg&w=1440",
          "width": 1440,
          "height": 960,
          "title": null,
          "attribution": null,
          "isCached": true
        }
      ],
      "content": "\r\n",
      "type": "article",
      "ampWebUrl": "https://www.washingtonpost.com/politics/2020/11/13/why-did-polls-undercount-trump-voters/?outputType=amp",
      "cdnAmpWebUrl": "https://www-washingtonpost-com.cdn.ampproject.org/c/s/www.washingtonpost.com/politics/2020/11/13/why-did-polls-undercount-trump-voters/?outputType=amp",
      "publishedDateTime": "2020-11-13T04:09:00-08:00",
      "updatedDateTime": null,
      "provider": {
        "name": "Washington Post",
        "domain": "washingtonpost.com",
        "images": [
          {
            "url": "https://smartableai.github.io/election/assets/images/organizations/washingtonpost.com-50x50.jpg",
            "width": 50,
            "height": 50,
            "title": null,
            "attribution": null,
            "isCached": false
          }
        ],
        "publishers": null,
        "authors": null
      },
      "locale": "en-us",
      "categories": [
        "news"
      ],
      "topics": [
        "Election",
        "Donald Trump"
      ]
    },
    {
      "path": "_news/2020-11-13-sheldon-adelsons-las-vegas-review-journal-tells-trump-to-stop-delaying-the-inevitable.md",
      "title": "Sheldon Adelson’s Las Vegas Review-Journal Tells Trump To Stop Delaying ‘The Inevitable’",
      "excerpt": "The billionaire casino tycoon was one of Trump’s biggest donors ahead of the presidential election. Now the newspaper he owns is saying that Trump should concede.",
      "sourceUrl": null,
      "webUrl": "https://www.forbes.com/sites/willyakowicz/2020/11/13/sheldon-adelsons-las-vegas-review-journal-tells-trump-to-stop-delaying-the-inevitable/",
      "originalUrl": "https://www.forbes.com/sites/willyakowicz/2020/11/13/sheldon-adelsons-las-vegas-review-journal-tells-trump-to-stop-delaying-the-inevitable/",
      "featuredContent": null,
      "highlight": null,
      "heat": 136,
      "tags": null,
      "images": [
        {
          "url": "https://thumbor.forbes.com/thumbor/fit-in/1200x0/filters%3Aformat%28jpg%29/https%3A%2F%2Fspecials-images.forbesimg.com%2Fimageserve%2F5fadfccc6304390c09f137af%2F0x0.jpg",
          "width": 1200,
          "height": 800,
          "title": null,
          "attribution": null,
          "isCached": true
        }
      ],
      "content": "\r\n",
      "type": "article",
      "ampWebUrl": "https://www.forbes.com/sites/willyakowicz/2020/11/13/sheldon-adelsons-las-vegas-review-journal-tells-trump-to-stop-delaying-the-inevitable/amp/",
      "cdnAmpWebUrl": "https://www-forbes-com.cdn.ampproject.org/c/s/www.forbes.com/sites/willyakowicz/2020/11/13/sheldon-adelsons-las-vegas-review-journal-tells-trump-to-stop-delaying-the-inevitable/amp/",
      "publishedDateTime": "2020-11-13T03:30:00-08:00",
      "updatedDateTime": null,
      "provider": {
        "name": "Forbes",
        "domain": "forbes.com",
        "images": [
          {
            "url": "https://smartableai.github.io/election/assets/images/organizations/forbes.com-50x50.jpg",
            "width": 50,
            "height": 50,
            "title": null,
            "attribution": null,
            "isCached": false
          }
        ],
        "publishers": null,
        "authors": null
      },
      "locale": "en-us",
      "categories": [
        "news"
      ],
      "topics": [
        "Election",
        "Donald Trump"
      ]
    },
    {
      "path": "_news/2020-11-13-far-right-protesters-counterdemonstrators-plan-to-gather-saturday-in-dc-amid-pro-trump-rallies.md",
      "title": "Far-right protesters, counterdemonstrators plan to gather Saturday in D.C. amid pro-Trump rallies",
      "excerpt": "The events have been promoted by far-right media personalities, white nationalists and conspiracists — several of whom announced plans to attend. Counterdemonstrations organized by anti-fascist and anti-racism groups are being planned nearby.",
      "sourceUrl": null,
      "webUrl": "https://www.washingtonpost.com/local/maga-dc-protests/2020/11/12/ca7a16fc-2455-11eb-8672-c281c7a2c96e_story.html",
      "originalUrl": "https://www.washingtonpost.com/local/maga-dc-protests/2020/11/12/ca7a16fc-2455-11eb-8672-c281c7a2c96e_story.html",
      "featuredContent": null,
      "highlight": null,
      "heat": 112,
      "tags": null,
      "images": [
        {
          "url": "https://www.washingtonpost.com/wp-apps/imrs.php?src=https://arc-anglerfish-washpost-prod-washpost.s3.amazonaws.com/public/6HLV6YAYPMI6XC62QFGKK3QTRM.jpg&w=1440",
          "width": 1440,
          "height": 961,
          "title": null,
          "attribution": null,
          "isCached": true
        }
      ],
      "content": "\r\n",
      "type": "article",
      "ampWebUrl": "https://www.washingtonpost.com/local/maga-dc-protests/2020/11/12/ca7a16fc-2455-11eb-8672-c281c7a2c96e_story.html?outputType=amp",
      "cdnAmpWebUrl": "https://www-washingtonpost-com.cdn.ampproject.org/c/s/www.washingtonpost.com/local/maga-dc-protests/2020/11/12/ca7a16fc-2455-11eb-8672-c281c7a2c96e_story.html?outputType=amp",
      "publishedDateTime": "2020-11-12T20:48:00-08:00",
      "updatedDateTime": null,
      "provider": {
        "name": "Washington Post",
        "domain": "washingtonpost.com",
        "images": [
          {
            "url": "https://smartableai.github.io/election/assets/images/organizations/washingtonpost.com-50x50.jpg",
            "width": 50,
            "height": 50,
            "title": null,
            "attribution": null,
            "isCached": false
          }
        ],
        "publishers": null,
        "authors": null
      },
      "locale": "en-us",
      "categories": [
        "news"
      ],
      "topics": [
        "Election",
        "Donald Trump"
      ]
    },
    {
      "path": "_news/2020-11-13-obama-trumps-fraud-claims-delegitimizing-democracy.md",
      "title": "Obama: Trump's fraud claims delegitimizing democracy",
      "excerpt": "CNN's Wolf Blitzer speaks with Cindy McCain, widow of late Sen. John McCain, about President Donald Trump's refusal to concede to President-elect Joe Biden.",
      "sourceUrl": null,
      "webUrl": "https://www.cnn.com/videos/media/2020/11/13/cindy-mccain-obama-trump-biden-2020-election-sot-vpx-tsr.cnn",
      "originalUrl": "https://www.cnn.com/videos/media/2020/11/13/cindy-mccain-obama-trump-biden-2020-election-sot-vpx-tsr.cnn",
      "featuredContent": null,
      "highlight": {
        "text": "Democratic Voice",
        "textColor": "#FFFFFF",
        "backgroundColor": "#0015BC"
      },
      "heat": 135,
      "tags": null,
      "images": [
        {
          "url": "https://cdn.cnn.com/cnnnext/dam/assets/201112191137-obama-cbs-super-tease.jpg",
          "width": 1100,
          "height": 619,
          "title": null,
          "attribution": null,
          "isCached": true
        }
      ],
      "content": "\r\n",
      "type": "article",
      "ampWebUrl": "https://amp.cnn.com/cnn/videos/media/2020/11/13/cindy-mccain-obama-trump-biden-2020-election-sot-vpx-tsr.cnn",
      "cdnAmpWebUrl": "https://amp-cnn-com.cdn.ampproject.org/c/s/amp.cnn.com/cnn/videos/media/2020/11/13/cindy-mccain-obama-trump-biden-2020-election-sot-vpx-tsr.cnn",
      "publishedDateTime": "2020-11-12T16:39:00-08:00",
      "updatedDateTime": null,
      "provider": {
        "name": "CNN",
        "domain": "cnn.com",
        "images": [
          {
            "url": "https://smartableai.github.io/election/assets/images/organizations/cnn.com-50x50.jpg",
            "width": 50,
            "height": 50,
            "title": null,
            "attribution": null,
            "isCached": false
          }
        ],
        "publishers": null,
        "authors": null
      },
      "locale": "en-us",
      "categories": [
        "news"
      ],
      "topics": [
        "Election",
        "Donald Trump",
        "Democratic Voice"
      ]
    },
    {
      "path": "_news/2020-11-13-senate-could-vote-on-trumps-fed-nominees-next-week-bloomberg-news.md",
      "title": "Senate could vote on Trump's Fed nominees next week: Bloomberg News",
      "excerpt": "The Republican leadership at the U.S. Senate has discussed holding a vote on U.S. President Donald Trump’s nominees to the Federal Reserve as early as next week, Bloomberg News reported Thursday, citing Republican Senator John Cornyn.",
      "sourceUrl": null,
      "webUrl": "https://www.reuters.com/article/usa-fed-nominees/senate-could-vote-on-trumps-fed-nominees-next-week-bloomberg-news-idUSL1N2HY2Q5",
      "originalUrl": "https://www.reuters.com/article/usa-fed-nominees/senate-could-vote-on-trumps-fed-nominees-next-week-bloomberg-news-idUSL1N2HY2Q5",
      "featuredContent": null,
      "highlight": null,
      "heat": 105,
      "tags": null,
      "images": null,
      "content": "\r\n",
      "type": "article",
      "ampWebUrl": "https://mobile.reuters.com/article/amp/idUSL1N2HY2Q5",
      "cdnAmpWebUrl": "https://mobile-reuters-com.cdn.ampproject.org/c/s/mobile.reuters.com/article/amp/idUSL1N2HY2Q5",
      "publishedDateTime": "2020-11-12T16:11:00-08:00",
      "updatedDateTime": null,
      "provider": {
        "name": "Reuters",
        "domain": "reuters.com",
        "images": [
          {
            "url": "https://smartableai.github.io/election/assets/images/organizations/reuters.com-50x50.jpg",
            "width": 50,
            "height": 50,
            "title": null,
            "attribution": null,
            "isCached": false
          }
        ],
        "publishers": null,
        "authors": null
      },
      "locale": "en-us",
      "categories": [
        "news"
      ],
      "topics": [
        "Election",
        "Donald Trump"
      ]
    },
    {
      "path": "_news/2020-11-13-john-mccains-widow-says-its-time-for-trump-to-accept-the-results-and-get-on-with-the-healing.md",
      "title": "John McCain's widow says it's time for Trump to 'accept the results and get on with the healing'",
      "excerpt": "Cindy McCain described Joe Biden as \"a man of honor\" who would \"heal the wounds caused by the outgoing administration.\"",
      "sourceUrl": null,
      "webUrl": "https://www.businessinsider.com/john-mccain-trump-accept-the-results-cindy-2020-11",
      "originalUrl": "https://www.businessinsider.com/john-mccain-trump-accept-the-results-cindy-2020-11",
      "featuredContent": null,
      "highlight": null,
      "heat": 112,
      "tags": null,
      "images": [
        {
          "url": "https://i.insider.com/5fad9cdf1e8d500019813396?width=1200&format=jpeg",
          "width": 1200,
          "height": 600,
          "title": null,
          "attribution": null,
          "isCached": true
        }
      ],
      "content": "\r\n",
      "type": "article",
      "ampWebUrl": "https://www.businessinsider.com/john-mccain-trump-accept-the-results-cindy-2020-11?amp",
      "cdnAmpWebUrl": "https://www-businessinsider-com.cdn.ampproject.org/c/s/www.businessinsider.com/john-mccain-trump-accept-the-results-cindy-2020-11?amp",
      "publishedDateTime": "2020-11-12T14:18:00-08:00",
      "updatedDateTime": null,
      "provider": {
        "name": "Business Insider",
        "domain": "businessinsider.com",
        "images": [
          {
            "url": "https://smartableai.github.io/election/assets/images/organizations/businessinsider.com-50x50.jpg",
            "width": 50,
            "height": 50,
            "title": null,
            "attribution": null,
            "isCached": false
          }
        ],
        "publishers": null,
        "authors": null
      },
      "locale": "en-us",
      "categories": [
        "news"
      ],
      "topics": [
        "Election",
        "Donald Trump"
      ]
    },
    {
      "path": "_news/2020-11-13-nikki-haley-a-high-profile-republican-and-possible-2024-presidential-hopeful-has-remained-silent-about-trumps-unfounded-election-fraud-claims.md",
      "title": "Nikki Haley, a high-profile Republican and possible 2024 presidential hopeful, has remained silent about Trump's unfounded election fraud claims",
      "excerpt": "UN ambassador hasn't commented on Trump's refusal to concede the election, sticking instead to tweets about GOP victories down ballot.",
      "sourceUrl": null,
      "webUrl": "https://www.businessinsider.com/nikki-haley-silent-on-trump-election-fraud-claims-2020-11",
      "originalUrl": "https://www.businessinsider.com/nikki-haley-silent-on-trump-election-fraud-claims-2020-11",
      "featuredContent": null,
      "highlight": null,
      "heat": 103,
      "tags": null,
      "images": [
        {
          "url": "https://i.insider.com/5fad69b4df90d000183781b4?width=1200&format=jpeg",
          "width": 1024,
          "height": 512,
          "title": null,
          "attribution": null,
          "isCached": true
        }
      ],
      "content": "\r\n",
      "type": "article",
      "ampWebUrl": "https://www.businessinsider.com/nikki-haley-silent-on-trump-election-fraud-claims-2020-11?amp",
      "cdnAmpWebUrl": "https://www-businessinsider-com.cdn.ampproject.org/c/s/www.businessinsider.com/nikki-haley-silent-on-trump-election-fraud-claims-2020-11?amp",
      "publishedDateTime": "2020-11-12T14:17:00-08:00",
      "updatedDateTime": null,
      "provider": {
        "name": "Business Insider",
        "domain": "businessinsider.com",
        "images": [
          {
            "url": "https://smartableai.github.io/election/assets/images/organizations/businessinsider.com-50x50.jpg",
            "width": 50,
            "height": 50,
            "title": null,
            "attribution": null,
            "isCached": false
          }
        ],
        "publishers": null,
        "authors": null
      },
      "locale": "en-us",
      "categories": [
        "news"
      ],
      "topics": [
        "Election",
        "Donald Trump"
      ]
    },
    {
      "path": "_news/2020-11-13-trump-has-tried-to-coopt-the-army-this-new-museum-shows-why-that-wont-be-easy.md",
      "title": "Trump has tried to coopt the Army. This new museum shows why that won’t be easy.",
      "excerpt": "Smart, clear and a little institutional, the museum at Fort Belvoir is a major addition to the cultural landscape.",
      "sourceUrl": null,
      "webUrl": "https://www.washingtonpost.com/entertainment/museums/national-army-museum-opens-fort-belvoir/2020/11/11/cd07ea06-2442-11eb-952e-0c475972cfc0_story.html",
      "originalUrl": "https://www.washingtonpost.com/entertainment/museums/national-army-museum-opens-fort-belvoir/2020/11/11/cd07ea06-2442-11eb-952e-0c475972cfc0_story.html",
      "featuredContent": null,
      "highlight": null,
      "heat": 120,
      "tags": null,
      "images": [
        {
          "url": "https://www.washingtonpost.com/wp-apps/imrs.php?src=https://arc-anglerfish-washpost-prod-washpost.s3.amazonaws.com/public/L7O4NDQMZEI6XNAERUPGOXWHAE.jpg&w=1440",
          "width": 1440,
          "height": 995,
          "title": null,
          "attribution": null,
          "isCached": true
        }
      ],
      "content": "\r\n",
      "type": "article",
      "ampWebUrl": "https://www.washingtonpost.com/entertainment/museums/national-army-museum-opens-fort-belvoir/2020/11/11/cd07ea06-2442-11eb-952e-0c475972cfc0_story.html?outputType=amp",
      "cdnAmpWebUrl": "https://www-washingtonpost-com.cdn.ampproject.org/c/s/www.washingtonpost.com/entertainment/museums/national-army-museum-opens-fort-belvoir/2020/11/11/cd07ea06-2442-11eb-952e-0c475972cfc0_story.html?outputType=amp",
      "publishedDateTime": "2020-11-12T12:16:00-08:00",
      "updatedDateTime": null,
      "provider": {
        "name": "Washington Post",
        "domain": "washingtonpost.com",
        "images": [
          {
            "url": "https://smartableai.github.io/election/assets/images/organizations/washingtonpost.com-50x50.jpg",
            "width": 50,
            "height": 50,
            "title": null,
            "attribution": null,
            "isCached": false
          }
        ],
        "publishers": null,
        "authors": null
      },
      "locale": "en-us",
      "categories": [
        "news"
      ],
      "topics": [
        "Election",
        "Donald Trump"
      ]
    },
    {
      "path": "_news/2020-11-13-donald-trump-lost-the-presidency-residents-and-realtors-of-trump-tower-think-it-may-become-valuable-again.md",
      "title": "Donald Trump lost the presidency. Residents and realtors of Trump Tower think it may become valuable again.",
      "excerpt": "\"I'm hoping that if he doesn't come back there, and we take his name off the building, we could have a wonderful spot to live again,\" said one owner.",
      "sourceUrl": null,
      "webUrl": "https://www.businessinsider.com/trump-lost-presidency-future-of-trump-tower-may-be-bright-2020-11",
      "originalUrl": "https://www.businessinsider.com/trump-lost-presidency-future-of-trump-tower-may-be-bright-2020-11",
      "featuredContent": null,
      "highlight": null,
      "heat": 127,
      "tags": null,
      "images": [
        {
          "url": "https://i.insider.com/5fac0ab3b09abb0018625f46?width=1200&format=jpeg",
          "width": 1200,
          "height": 600,
          "title": null,
          "attribution": null,
          "isCached": true
        }
      ],
      "content": "\r\n",
      "type": "article",
      "ampWebUrl": "https://www.businessinsider.com/trump-lost-presidency-future-of-trump-tower-may-be-bright-2020-11?amp",
      "cdnAmpWebUrl": "https://www-businessinsider-com.cdn.ampproject.org/c/s/www.businessinsider.com/trump-lost-presidency-future-of-trump-tower-may-be-bright-2020-11?amp",
      "publishedDateTime": "2020-11-12T11:01:00-08:00",
      "updatedDateTime": null,
      "provider": {
        "name": "Business Insider",
        "domain": "businessinsider.com",
        "images": [
          {
            "url": "https://smartableai.github.io/election/assets/images/organizations/businessinsider.com-50x50.jpg",
            "width": 50,
            "height": 50,
            "title": null,
            "attribution": null,
            "isCached": false
          }
        ],
        "publishers": null,
        "authors": null
      },
      "locale": "en-us",
      "categories": [
        "news"
      ],
      "topics": [
        "Election",
        "Donald Trump"
      ]
    },
    {
      "path": "_news/2020-11-13-how-long-can-republicans-keep-helping-trump-delegitimize-the-election.md",
      "title": "How long can Republicans keep helping Trump delegitimize the election?",
      "excerpt": "There are some cracks starting to show – but strong political reasons for Republicans to hang on until Georgia Senate runoffs in January",
      "sourceUrl": null,
      "webUrl": "https://www.washingtonpost.com/politics/2020/11/12/how-long-can-republicans-keep-helping-trump-delegitimize-election/",
      "originalUrl": "https://www.washingtonpost.com/politics/2020/11/12/how-long-can-republicans-keep-helping-trump-delegitimize-election/",
      "featuredContent": null,
      "highlight": null,
      "heat": 440,
      "tags": null,
      "images": [
        {
          "url": "https://www.washingtonpost.com/wp-apps/imrs.php?src=https://arc-anglerfish-washpost-prod-washpost.s3.amazonaws.com/public/X2BIDWBEJYI6XHCKBXDCILCICQ.jpg&w=1440",
          "width": 1440,
          "height": 960,
          "title": null,
          "attribution": null,
          "isCached": true
        }
      ],
      "content": "\r\n",
      "type": "article",
      "ampWebUrl": "https://www.washingtonpost.com/politics/2020/11/12/how-long-can-republicans-keep-helping-trump-delegitimize-election/?outputType=amp",
      "cdnAmpWebUrl": "https://www-washingtonpost-com.cdn.ampproject.org/c/s/www.washingtonpost.com/politics/2020/11/12/how-long-can-republicans-keep-helping-trump-delegitimize-election/?outputType=amp",
      "publishedDateTime": "2020-11-12T08:44:00-08:00",
      "updatedDateTime": null,
      "provider": {
        "name": "Washington Post",
        "domain": "washingtonpost.com",
        "images": [
          {
            "url": "https://smartableai.github.io/election/assets/images/organizations/washingtonpost.com-50x50.jpg",
            "width": 50,
            "height": 50,
            "title": null,
            "attribution": null,
            "isCached": false
          }
        ],
        "publishers": null,
        "authors": null
      },
      "locale": "en-us",
      "categories": [
        "news"
      ],
      "topics": [
        "Election",
        "Donald Trump"
      ]
    },
    {
      "path": "_news/2020-11-12-obama-says-trump-used-his-birther-lie-to-give-millions-of-white-americans-spooked-by-a-black-president-an-elixir-for-their-racial-anxiety.md",
      "title": "Obama says Trump used his 'birther' lie to give millions of white Americans 'spooked' by a Black president an 'elixir for their racial anxiety'",
      "excerpt": "\"For millions of Americans spooked by a Black man in the White House, he promised an elixir for their racial anxiety,\" Obama writes of Trump.",
      "sourceUrl": null,
      "webUrl": "https://www.businessinsider.com/obama-says-trumps-birther-lie-weaponized-white-americans-racism-2020-11",
      "originalUrl": "https://www.businessinsider.com/obama-says-trumps-birther-lie-weaponized-white-americans-racism-2020-11",
      "featuredContent": null,
      "highlight": null,
      "heat": 89,
      "tags": null,
      "images": [
        {
          "url": "https://i.insider.com/5f986f100c60aa00190d49db?width=1200&format=jpeg",
          "width": 1200,
          "height": 600,
          "title": null,
          "attribution": null,
          "isCached": true
        }
      ],
      "content": "\r\n",
      "type": "article",
      "ampWebUrl": "https://www.businessinsider.com/obama-says-trumps-birther-lie-weaponized-white-americans-racism-2020-11?amp",
      "cdnAmpWebUrl": "https://www-businessinsider-com.cdn.ampproject.org/c/s/www.businessinsider.com/obama-says-trumps-birther-lie-weaponized-white-americans-racism-2020-11?amp",
      "publishedDateTime": "2020-11-12T07:57:00-08:00",
      "updatedDateTime": null,
      "provider": {
        "name": "Business Insider",
        "domain": "businessinsider.com",
        "images": [
          {
            "url": "https://smartableai.github.io/election/assets/images/organizations/businessinsider.com-50x50.jpg",
            "width": 50,
            "height": 50,
            "title": null,
            "attribution": null,
            "isCached": false
          }
        ],
        "publishers": null,
        "authors": null
      },
      "locale": "en-us",
      "categories": [
        "news"
      ],
      "topics": [
        "Election",
        "Donald Trump"
      ]
    },
    {
      "path": "_news/2020-11-12-election-2020-live-updates-bolton-says-republicans-coddling-trump-georgia-will-do-hand-recount.md",
      "title": "Election 2020 live updates: Bolton says Republicans 'coddling' Trump; Georgia will do hand recount",
      "excerpt": "Both Trump and Biden took part in Veterans Day ceremonies Wednesday. Biden continues the transition process as Trump contests the election.",
      "sourceUrl": null,
      "webUrl": "https://www.usatoday.com/story/news/politics/elections/2020/11/11/election-2020-updates-biden-transition-trump-honors-veterans-day/6246438002/",
      "originalUrl": "https://www.usatoday.com/story/news/politics/elections/2020/11/11/election-2020-updates-biden-transition-trump-honors-veterans-day/6246438002/",
      "featuredContent": null,
      "highlight": null,
      "heat": 166,
      "tags": null,
      "images": [
        {
          "url": "https://www.gannett-cdn.com/presto/2020/11/11/USAT/41cea45e-fe21-4819-aa48-7f740386034d-GTY_1285134487.jpg?auto=webp&crop=5471,3078,x0,y278&format=pjpg&width=1200",
          "width": 1200,
          "height": 675,
          "title": null,
          "attribution": null,
          "isCached": true
        }
      ],
      "content": "\r\n",
      "type": "article",
      "ampWebUrl": "https://amp.usatoday.com/amp/6246438002",
      "cdnAmpWebUrl": "https://amp-usatoday-com.cdn.ampproject.org/c/s/amp.usatoday.com/amp/6246438002",
      "publishedDateTime": "2020-11-11T20:37:00-08:00",
      "updatedDateTime": null,
      "provider": {
        "name": "The Clarion-Ledger",
        "domain": "usatoday.com",
        "images": [
          {
            "url": "https://smartableai.github.io/election/assets/images/organizations/usatoday.com-50x50.jpg",
            "width": 50,
            "height": 50,
            "title": null,
            "attribution": null,
            "isCached": false
          }
        ],
        "publishers": null,
        "authors": null
      },
      "locale": "en-us",
      "categories": [
        "news"
      ],
      "topics": [
        "Election",
        "Donald Trump"
      ]
    },
    {
      "path": "_news/2020-11-12-donald-trump-supporters-can-get-free-food-at-kentucky-restaurants-owned-by-the-same-couple-but-theres-a-catch.md",
      "title": "Donald Trump supporters can get free food at Kentucky restaurants owned by the same couple. But there's a catch.",
      "excerpt": "Louisville restaurant owners Troy King and Selena Johnson are offering free food to anyone who trades in Donald Trump merchandise.",
      "sourceUrl": null,
      "webUrl": "https://www.usatoday.com/story/news/nation/2020/11/11/kentucky-restaurant-free-meal-donald-trump-maga-supporters/6261164002/",
      "originalUrl": "https://www.usatoday.com/story/news/nation/2020/11/11/kentucky-restaurant-free-meal-donald-trump-maga-supporters/6261164002/",
      "featuredContent": null,
      "highlight": null,
      "heat": 124,
      "tags": null,
      "images": [
        {
          "url": "https://www.gannett-cdn.com/presto/2020/01/21/PLOU/959e4d35-d555-469a-98b0-632ce95f5d86-0116DINE_6ForksBurgerCo02_DRL.JPG?auto=webp&crop=2999,1687,x0,y0&format=pjpg&width=1200",
          "width": 1200,
          "height": 675,
          "title": null,
          "attribution": null,
          "isCached": true
        }
      ],
      "content": "\r\n",
      "type": "article",
      "ampWebUrl": "https://amp.usatoday.com/amp/6261164002",
      "cdnAmpWebUrl": "https://amp-usatoday-com.cdn.ampproject.org/c/s/amp.usatoday.com/amp/6261164002",
      "publishedDateTime": "2020-11-11T20:26:00-08:00",
      "updatedDateTime": null,
      "provider": {
        "name": "USA Today",
        "domain": "usatoday.com",
        "images": [
          {
            "url": "https://smartableai.github.io/election/assets/images/organizations/usatoday.com-50x50.jpg",
            "width": 50,
            "height": 50,
            "title": null,
            "attribution": null,
            "isCached": false
          }
        ],
        "publishers": null,
        "authors": null
      },
      "locale": "en-us",
      "categories": [
        "news"
      ],
      "topics": [
        "Election",
        "Donald Trump"
      ]
    },
    {
      "path": "_news/2020-11-12-trump-endorses-ronna-mcdaniel-to-remain-rnc-chair.md",
      "title": "Trump endorses Ronna McDaniel to remain RNC chair",
      "excerpt": "U.S. President Donald Trump on Wednesday endorsed Republican National Commmittee chair Ronna McDaniel to stay on in her position, crediting her with much of the support Trump received in the presidential election that he lost but is contesting.",
      "sourceUrl": null,
      "webUrl": "https://www.reuters.com/article/us-usa-election-trump-idUSKBN27S01C",
      "originalUrl": "https://www.reuters.com/article/us-usa-election-trump-idUSKBN27S01C",
      "featuredContent": null,
      "highlight": null,
      "heat": 125,
      "tags": null,
      "images": [
        {
          "url": "https://s1.reutersmedia.net/resources/r/?m=02&d=20201112&t=2&i=1540909087&w=&fh=545px&fw=&ll=&pl=&sq=&r=LYNXMPEGAB011",
          "width": 833,
          "height": 545,
          "title": null,
          "attribution": null,
          "isCached": true
        }
      ],
      "content": "\r\n",
      "type": "article",
      "ampWebUrl": "https://mobile.reuters.com/article/amp/idUSKBN27S01C",
      "cdnAmpWebUrl": "https://mobile-reuters-com.cdn.ampproject.org/c/s/mobile.reuters.com/article/amp/idUSKBN27S01C",
      "publishedDateTime": "2020-11-11T16:44:00-08:00",
      "updatedDateTime": null,
      "provider": {
        "name": "Reuters",
        "domain": "reuters.com",
        "images": [
          {
            "url": "https://smartableai.github.io/election/assets/images/organizations/reuters.com-50x50.jpg",
            "width": 50,
            "height": 50,
            "title": null,
            "attribution": null,
            "isCached": false
          }
        ],
        "publishers": null,
        "authors": null
      },
      "locale": "en-us",
      "categories": [
        "news"
      ],
      "topics": [
        "Election",
        "Donald Trump"
      ]
    },
    {
      "path": "_news/2020-11-12-trump-lawyers-suffer-embarrassing-rebukes-from-judges-over-voter-fraud-claims.md",
      "title": "Trump lawyers suffer embarrassing rebukes from judges over voter fraud claims",
      "excerpt": "Over and over again over the past week, Trump's lawyers have been forced to account for their lack of evidence. It often hasn't gone well.",
      "sourceUrl": null,
      "webUrl": "https://www.washingtonpost.com/politics/2020/11/11/trump-lawyers-suffer-embarrassing-rebukes-judges-over-voter-fraud-claims/",
      "originalUrl": "https://www.washingtonpost.com/politics/2020/11/11/trump-lawyers-suffer-embarrassing-rebukes-judges-over-voter-fraud-claims/",
      "featuredContent": null,
      "highlight": null,
      "heat": 202,
      "tags": null,
      "images": [
        {
          "url": "https://www.washingtonpost.com/wp-apps/imrs.php?src=https://arc-anglerfish-washpost-prod-washpost.s3.amazonaws.com/public/4X74IKWYGMI6NIHG2UBNM5I3ZA&w=1440",
          "width": 1440,
          "height": 960,
          "title": null,
          "attribution": null,
          "isCached": true
        }
      ],
      "content": "\r\n",
      "type": "article",
      "ampWebUrl": "https://www.washingtonpost.com/politics/2020/11/11/trump-lawyers-suffer-embarrassing-rebukes-judges-over-voter-fraud-claims/?outputType=amp",
      "cdnAmpWebUrl": "https://www-washingtonpost-com.cdn.ampproject.org/c/s/www.washingtonpost.com/politics/2020/11/11/trump-lawyers-suffer-embarrassing-rebukes-judges-over-voter-fraud-claims/?outputType=amp",
      "publishedDateTime": "2020-11-11T08:57:00-08:00",
      "updatedDateTime": null,
      "provider": {
        "name": "Washington Post",
        "domain": "washingtonpost.com",
        "images": [
          {
            "url": "https://smartableai.github.io/election/assets/images/organizations/washingtonpost.com-50x50.jpg",
            "width": 50,
            "height": 50,
            "title": null,
            "attribution": null,
            "isCached": false
          }
        ],
        "publishers": null,
        "authors": null
      },
      "locale": "en-us",
      "categories": [
        "news"
      ],
      "topics": [
        "Election",
        "Donald Trump"
      ]
    },
    {
      "path": "_news/2020-11-11-parler-mewe-gab-gain-momentum-as-conservative-social-media-alternatives-in-post-trump-age.md",
      "title": "Parler, MeWe, Gab gain momentum as conservative social media alternatives in post-Trump age",
      "excerpt": "The rise of conservative-friendly platform Parler raises the specter of further political polarization through digital means.",
      "sourceUrl": null,
      "webUrl": "https://www.usatoday.com/story/tech/2020/11/11/parler-mewe-gab-social-media-trump-election-facebook-twitter/6232351002/",
      "originalUrl": "https://www.usatoday.com/story/tech/2020/11/11/parler-mewe-gab-social-media-trump-election-facebook-twitter/6232351002/",
      "featuredContent": null,
      "highlight": null,
      "heat": 135,
      "tags": null,
      "images": [
        {
          "url": "https://www.gannett-cdn.com/presto/2020/09/18/USAT/8c399606-d7e9-41de-bdad-fa14b9a11576-AP_Election_2020_Social_Media.jpg?auto=webp&crop=2050,1154,x0,y50&format=pjpg&width=1200",
          "width": 1200,
          "height": 676,
          "title": null,
          "attribution": null,
          "isCached": true
        }
      ],
      "content": "\r\n",
      "type": "article",
      "ampWebUrl": "https://amp.usatoday.com/amp/6232351002",
      "cdnAmpWebUrl": "https://amp-usatoday-com.cdn.ampproject.org/c/s/amp.usatoday.com/amp/6232351002",
      "publishedDateTime": "2020-11-11T01:20:00-08:00",
      "updatedDateTime": null,
      "provider": {
        "name": "USA Today",
        "domain": "usatoday.com",
        "images": [
          {
            "url": "https://smartableai.github.io/election/assets/images/organizations/usatoday.com-50x50.jpg",
            "width": 50,
            "height": 50,
            "title": null,
            "attribution": null,
            "isCached": false
          }
        ],
        "publishers": null,
        "authors": null
      },
      "locale": "en-us",
      "categories": [
        "news"
      ],
      "topics": [
        "Election",
        "Donald Trump"
      ]
    },
    {
      "path": "_news/2020-11-11-fox-news-cuts-away-from-trump-campaign-news-conference-cant-in-good-countenance-continue-showing-this.md",
      "title": "Fox News cuts away from Trump campaign news conference: 'Can't in good countenance continue showing this'",
      "excerpt": "Fox News anchor Neil Cavuto broke in and cut away from the news conference after \"explosive charges\" were made about voter fraud without evidence.",
      "sourceUrl": null,
      "webUrl": "https://www.usatoday.com/story/entertainment/tv/2020/11/09/fox-cuts-coverage-kayleigh-mcenany-trump-campaign-press-conference/6228124002/",
      "originalUrl": "https://www.usatoday.com/story/entertainment/tv/2020/11/09/fox-cuts-coverage-kayleigh-mcenany-trump-campaign-press-conference/6228124002/",
      "featuredContent": null,
      "highlight": null,
      "heat": 108,
      "tags": null,
      "images": [
        {
          "url": "https://www.gannett-cdn.com/presto/2020/11/09/USAT/c71df6e1-0af4-437e-8010-343af0b5c535-Fox_News.PNG?auto=webp&crop=981,552,x207,y0&format=pjpg&width=1200",
          "width": 1200,
          "height": 675,
          "title": null,
          "attribution": null,
          "isCached": true
        }
      ],
      "content": "\r\n",
      "type": "article",
      "ampWebUrl": "https://amp.usatoday.com/amp/6228124002",
      "cdnAmpWebUrl": "https://amp-usatoday-com.cdn.ampproject.org/c/s/amp.usatoday.com/amp/6228124002",
      "publishedDateTime": "2020-11-11T01:18:00-08:00",
      "updatedDateTime": null,
      "provider": {
        "name": "Detroit Free Press",
        "domain": "usatoday.com",
        "images": [
          {
            "url": "https://smartableai.github.io/election/assets/images/organizations/usatoday.com-50x50.jpg",
            "width": 50,
            "height": 50,
            "title": null,
            "attribution": null,
            "isCached": false
          }
        ],
        "publishers": null,
        "authors": null
      },
      "locale": "en-us",
      "categories": [
        "news"
      ],
      "topics": [
        "Election",
        "Donald Trump"
      ]
    },
    {
      "path": "_news/2020-11-11-fact-check-video-shows-police-collecting-discarded-amazon-packages-not-thousands-of-trump-ballots.md",
      "title": "Fact check: Video shows police collecting discarded Amazon packages, not thousands of Trump ballots",
      "excerpt": "Social media users have claimed a video shows police finding thousands of ballots for U.S. President Donald Trump dumped in a field. This is not true; local police report that the footage actually shows discarded Amazon packages.",
      "sourceUrl": null,
      "webUrl": "https://www.reuters.com/article/uk-factcheck-packages-idUSKBN27Q2JC",
      "originalUrl": "https://www.reuters.com/article/uk-factcheck-packages-idUSKBN27Q2JC",
      "featuredContent": null,
      "highlight": null,
      "heat": 111,
      "tags": null,
      "images": [
        {
          "url": "https://s2.reutersmedia.net/resources/r/?m=02&d=20201110&t=2&i=1540721626&w=&fh=545px&fw=&ll=&pl=&sq=&r=LYNXMPEGA91F3",
          "width": 818,
          "height": 545,
          "title": null,
          "attribution": null,
          "isCached": true
        }
      ],
      "content": "\r\n",
      "type": "article",
      "ampWebUrl": "https://mobile.reuters.com/article/amp/idUSKBN27Q2JC",
      "cdnAmpWebUrl": "https://mobile-reuters-com.cdn.ampproject.org/c/s/mobile.reuters.com/article/amp/idUSKBN27Q2JC",
      "publishedDateTime": "2020-11-10T13:14:00-08:00",
      "updatedDateTime": null,
      "provider": {
        "name": "Reuters",
        "domain": "reuters.com",
        "images": [
          {
            "url": "https://smartableai.github.io/election/assets/images/organizations/reuters.com-50x50.jpg",
            "width": 50,
            "height": 50,
            "title": null,
            "attribution": null,
            "isCached": false
          }
        ],
        "publishers": null,
        "authors": null
      },
      "locale": "en-us",
      "categories": [
        "news"
      ],
      "topics": [
        "Election",
        "Donald Trump"
      ]
    }
  ],
  "nextPage": 2
}